emkonfig/__init__.py
emkonfig/config.py
emkonfig/external/hydra/instantiate.py
emkonfig/parsers.py
emkonfig/registry.py
emkonfig/utils.py
emkonfig-0.4.0.dist-info/METADATA
emkonfig-0.4.0.dist-info/WHEEL
emkonfig-0.4.0.dist-info/RECORD
