Metadata-Version: 2.1
Name: emkonfig
Version: 0.4.0
Summary: YAML template based configuration management tool
License: MIT
Author: Kıvanç Yüksel
Author-email: kivanc.yuksel@emkademy.com
Requires-Python: >=3.11
Classifier: Development Status :: 4 - Beta
Classifier: License :: OSI Approved :: MIT License
Classifier: Natural Language :: English
Classifier: Programming Language :: Python :: 3
Classifier: Programming Language :: Python :: 3.11
Classifier: Topic :: Software Development :: Libraries
Requires-Dist: omegaconf (>=2.3,<3.0)
Requires-Dist: universal-pathlib (>=0.2,<1.0)
